{
    "Status": true,
    "HttpStatus": 200,
    "Data": {
        "ShowAds": true,
        "Ads": [
		{
				"MonetizationId": 1,
				"MonetizerName": "Facebook Monetization",
				"AdAppKey": "451985113722015",
				"BannerAdKey": "451985113722015_451985557055304",
				"InterstitialAdKey": "451985113722015_451985643721962",
				"RewardedAdKey": "451985113722015_451985833721943",
				"NativeAdKey": "451985113722015_451985717055288"
			},
            {
                "MonetizationId": 6,
                "MonetizerName": "ironSource",
                "AdAppKey": "1720739cd",
                "BannerAdKey": "",
                "InterstitialAdKey": "",
                "RewardedAdKey": "",
                "NativeAdKey": ""
            },
			{
				"MonetizationId": 5,
				"MonetizerName": "UnityAds",
				"AdAppKey": "5003193",
				"BannerAdKey": "Banner_Android",
				"InterstitialAdKey": "Interstitial_Android",
				"RewardedAdKey": "Rewarded_Android",
				"NativeAdKey": ""
			}
        ]
    },
    "Message": "Data loaded."
}